netcdf2region/__init__.py
netcdf2region/compute_grid_weights.py
netcdf2region/netcdf2region.py
netcdf2region/data/ERA5_to_DOSE_admin1_weights.csv
netcdf2region/data/ERA5_to_GADM36_admin0_weights.csv
netcdf2region/data/ERA5_to_GADM36_admin1_weights.csv
netcdf2region/data/ISIMIP_to_DOSE_admin1_weights.csv
netcdf2region/data/ISIMIP_to_GADM36_admin0_weights.csv
netcdf2region/data/ISIMIP_to_GADM36_admin1_weights.csv
netcdf2region/data/__init__.py
netcdf2region-0.1.3.dist-info/METADATA
netcdf2region-0.1.3.dist-info/WHEEL
netcdf2region-0.1.3.dist-info/entry_points.txt
netcdf2region-0.1.3.dist-info/top_level.txt
netcdf2region-0.1.3.dist-info/RECORD
