Metadata-Version: 2.4
Name: netcdf2region
Version: 0.1.3
Summary: Aggregate NetCDF data to regions using spatial weights
Author-email: Jakob Wedemeyer <jakob.wedemeyer@pik-potsdam.de>
Requires-Dist: numpy
Requires-Dist: pandas
Requires-Dist: xarray
Requires-Dist: rasterio
Requires-Dist: geopandas
Requires-Dist: matplotlib
Requires-Dist: shapely
Requires-Dist: joblib
Requires-Dist: scipy
Requires-Dist: tqdm
Requires-Dist: netcdf4
